{
  "full name": "name",
  "name": "name",
  "roll id": "roll_no",
  "roll_no": "roll_no",
  "admission no": "roll_no",
  "registration id": "roll_no",
  "reg no.": "roll_no",
  "roll number": "roll_no",
  "mail-id": "email",
  "email": "email",
  "mail": "email",
  "e-mail": "email",
  "email id": "email",
  "id": "email",
  "mail address": "email",
  "enail address": "email",
  "gaurangi agrawal": "Gaurangi Agrawal",
  "satvika shrivastava": "Satvika Shrivastava",
  "anoushka chouksey": "Anoushka Chouksey",
  "shubhanshi bhandari": "Shubhanshi Bhandari",
  "tanishka singhal": "Tanishka Singhal"
}